linuxU.py
linuxU-0.1.1.dist-info/LICENSE
linuxU-0.1.1.dist-info/METADATA
linuxU-0.1.1.dist-info/WHEEL
linuxU-0.1.1.dist-info/top_level.txt
linuxU-0.1.1.dist-info/RECORD
