Metadata-Version: 2.1
Name: linuxU
Version: 0.1.1
Summary: Update, upgrade, autoremove etc. for GNU/Linux System
Home-page: https://github.com/ilteriskeskin/linuxU
Author: ilteriskeskin
Author-email: aliilteriskeskin@gmail.com
License: GPL-3.0
Platform: UNKNOWN
